geb/HRUs.py
geb/__init__.py
geb/artists.py
geb/calibrate.py
geb/cli.py
geb/data.py
geb/model.py
geb/multirun.py
geb/reporter.py
geb/sensitivity.py
geb/workflows.py
geb/agents/__init__.py
geb/agents/crop_farmers.py
geb/agents/decision_module.py
geb/agents/general.py
geb/agents/government.py
geb/agents/households.py
geb/agents/industry.py
geb/agents/livestock_farmers.py
geb/agents/market.py
geb/agents/reservoir_operators.py
geb/agents/town_managers.py
geb/hazards/driver.py
geb/hazards/floods/sfincs.py
geb/hydrology/__init__.py
geb/hydrology/evaporation.py
geb/hydrology/interception.py
geb/hydrology/lakes_res_small.py
geb/hydrology/lakes_reservoirs.py
geb/hydrology/landcover.py
geb/hydrology/plantFATE.py
geb/hydrology/potential_evapotranspiration.py
geb/hydrology/runoff_concentration.py
geb/hydrology/sealed_water.py
geb/hydrology/snow_frost.py
geb/hydrology/soil.py
geb/hydrology/water_demand.py
geb/hydrology/groundwater/__init__.py
geb/hydrology/groundwater/model.py
geb/hydrology/groundwater/linux/libmf6.so
geb/hydrology/groundwater/mac/libmf6.dylib
geb/hydrology/groundwater/mac_arm/libmf6.dylib
geb/hydrology/groundwater/windows/libmf6.dll
geb/hydrology/routing/__init__.py
geb/hydrology/routing/subroutines.py
geb/setup/__init__.py
geb/setup/geb.py
geb/setup/custom_models/__init__.py
geb/setup/custom_models/fairstream.py
geb/setup/workflows/__init__.py
geb/setup/workflows/conversions.py
geb/setup/workflows/crop_calendars.py
geb/setup/workflows/farmers.py
geb/setup/workflows/forcing.py
geb/setup/workflows/general.py
geb/setup/workflows/population.py
geb/setup/workflows/soilgrids.py
geb_model-1.0.0a8.dist-info/entry_points.txt
geb_model-1.0.0a8.dist-info/WHEEL
geb_model-1.0.0a8.dist-info/METADATA
geb_model-1.0.0a8.dist-info/RECORD
