Metadata-Version: 2.1
Name: geb-model
Version: 1.0.0a8
Summary: GEB simulates the environment, the individual behaviour of people, households and organizations - including their interactions - at small and large scale.
Author-email: Jens de Bruijn <jens.de.bruijn@vu.nl>, Maurice Kalthof <w.m.l.kalthof@vu.nl>, Veerle Bril <v.c.bril@vu.nl>, Tim Busker <tim.busker@vu.nl>
Requires-Python: >=3.11, <3.13
Classifier: Development Status :: 4 - Beta
Classifier: Intended Audience :: Developers
Classifier: Intended Audience :: Science/Research
Classifier: Topic :: Scientific/Engineering :: Hydrology
Classifier: License :: OSI Approved :: GNU General Public License v3 (GPLv3)
Classifier: Programming Language :: Python :: 3
Requires-Dist: cdsapi>=0.7.3
Requires-Dist: dask>=2024.6
Requires-Dist: deap>=1.4.1
Requires-Dist: flopy>=3.8.0
Requires-Dist: geopandas>=1.0.1
Requires-Dist: honeybees>=1.0.4
Requires-Dist: hydromt==0.10.0
Requires-Dist: hydromt-sfincs>=1.1.0
Requires-Dist: isimip-client>=1.0.1
Requires-Dist: matplotlib>=3.9.2
Requires-Dist: numba>=0.60.0
Requires-Dist: numpy<2
Requires-Dist: openpyxl>=3.1.2
Requires-Dist: pyarrow>=17.0.0
Requires-Dist: pybind11>=2.13.4
Requires-Dist: pyogrio>=0.9.0
Requires-Dist: pyyaml>=6.0.2
Requires-Dist: rasterio>=1.3.10
Requires-Dist: rioxarray>=0.17.0
Requires-Dist: s3fs>=2023.6.0
Requires-Dist: SALib>=1.4.8
Requires-Dist: scipy>=1.14.0
Requires-Dist: seaborn>=0.13.2
Requires-Dist: tbb4py>=2021.13.1
Requires-Dist: tqdm>=4.66.1
Requires-Dist: xarray>=2024.3.0
Requires-Dist: xclim>=0.52.0
Requires-Dist: xesmf>=0.8.4
Requires-Dist: xmipy>=1.5.0
Requires-Dist: zarr>=2.18.2
Requires-Dist: pytest ; extra == "dev"
Requires-Dist: ruff ; extra == "dev"
Requires-Dist: sphinx<8 ; extra == "docs"
Requires-Dist: sphinx-autodoc-typehints ; extra == "docs"
Requires-Dist: sphinxcontrib-autoprogram ; extra == "docs"
Requires-Dist: sphinx_rtd_theme ; extra == "docs"
Requires-Dist: sphinxcontrib-autoyaml ; extra == "docs"
Requires-Dist: pypandoc ; extra == "docs"
Requires-Dist: pgmpy>=0.1.24 ; extra == "fairstream"
Requires-Dist: daft>=0.1.2 ; extra == "fairstream"
Requires-Dist: opt-einsum>=3.3.0 ; extra == "fairstream"
Requires-Dist: cupy ; extra == "gpu"
Provides-Extra: dev
Provides-Extra: docs
Provides-Extra: fairstream
Provides-Extra: full
Provides-Extra: gpu
